[
  {
    "start": "2026-05-26T14:00:00Z",
    "stop": "2026-05-26T17:00:00Z",
    "project": "Deep Work",
    "tags": ["OBR", "Jetix-foundation", "doc"],
    "description": "Сбор + упаковка всех документов + плана"
  },
  {
    "start": "2026-05-26T17:00:00Z",
    "stop": "2026-05-26T17:30:00Z",
    "project": "Рутина",
    "tags": ["другое"],
    "description": "Рутина"
  },
  {
    "start": "2026-05-26T17:30:00Z",
    "stop": "2026-05-26T23:00:00Z",
    "project": "Deep Work",
    "tags": ["OBR", "Jetix-foundation", "doc"],
    "description": "Работа с документами"
  },
  {
    "start": "2026-05-26T23:00:00Z",
    "stop": "2026-05-27T00:00:00Z",
    "project": "Гулял",
    "tags": [],
    "description": "Прогулка"
  },
  {
    "start": "2026-05-27T00:00:00Z",
    "stop": "2026-05-27T02:00:00Z",
    "project": "Deep Work",
    "tags": ["SOZD", "OBR", "Jetix-foundation", "doc"],
    "description": "Сбор ответа Церену + обработка основных документов"
  },
  {
    "start": "2026-05-27T02:00:00Z",
    "stop": "2026-05-27T03:00:00Z",
    "project": "Гулял",
    "tags": [],
    "description": "Гулял, шёл домой"
  },
  {
    "start": "2026-05-27T03:00:00Z",
    "stop": "2026-05-27T05:00:00Z",
    "project": "Ебланил",
    "tags": ["телефон"],
    "description": "Втык в телефон"
  },
  {
    "start": "2026-05-27T05:00:00Z",
    "stop": "2026-05-27T10:20:00Z",
    "project": "Сон",
    "tags": ["глубокий"],
    "description": "Ночной сон"
  },
  {
    "start": "2026-05-27T10:20:00Z",
    "stop": "2026-05-27T11:00:00Z",
    "project": "Ебланил",
    "tags": ["телефон"],
    "description": "Втык в телефон"
  },
  {
    "start": "2026-05-27T11:00:00Z",
    "stop": "2026-05-27T11:30:00Z",
    "project": "Рутина",
    "tags": ["другое"],
    "description": "Рутина утренняя"
  },
  {
    "start": "2026-05-27T11:30:00Z",
    "stop": "2026-05-27T11:50:00Z",
    "project": "Зарядка",
    "tags": [],
    "description": "Утренняя зарядка"
  }
]
